pitrading/__init__.py
pitrading/cli.py
pitrading/holidays.py
pitrading/instrument.py
pitrading/pitrading.py
pitrading/tmp.py
pitrading/utils.py
pitrading-0.3.20.dist-info/licenses/AUTHORS.rst
pitrading-0.3.20.dist-info/licenses/LICENSE
pitrading-0.3.20.dist-info/METADATA
pitrading-0.3.20.dist-info/WHEEL
pitrading-0.3.20.dist-info/entry_points.txt
pitrading-0.3.20.dist-info/top_level.txt
pitrading-0.3.20.dist-info/RECORD
