Metadata-Version: 2.4
Name: pitrading
Version: 0.3.20
Summary: Handy trading utils for PiAsset
Home-page: https://code.piasset.net/saaltfiish/pitrading
Author: raiden
Author-email: raiden@dianyao.ai
License: MIT license
Keywords: pitrading
Classifier: Development Status :: 2 - Pre-Alpha
Classifier: Intended Audience :: Developers
Classifier: License :: OSI Approved :: MIT License
Classifier: Natural Language :: English
Classifier: Programming Language :: Python :: 3
Classifier: Programming Language :: Python :: 3.6
Classifier: Programming Language :: Python :: 3.7
Classifier: Programming Language :: Python :: 3.8
Requires-Python: >=3.6
License-File: LICENSE
License-File: AUTHORS.rst
Requires-Dist: redis
Requires-Dist: pyzmq
Requires-Dist: numpy
Requires-Dist: pandas
Requires-Dist: pytz
Requires-Dist: pi_utils
Requires-Dist: cos-python-sdk-v5
Requires-Dist: scipy
Requires-Dist: pdbpp
Dynamic: author
Dynamic: author-email
Dynamic: classifier
Dynamic: description
Dynamic: home-page
Dynamic: keywords
Dynamic: license
Dynamic: license-file
Dynamic: requires-dist
Dynamic: requires-python
Dynamic: summary
